xlpie/__init__.py
xlpie/excel_app.py
xlpie/excel_range.py
xlpie/excel_wb.py
xlpie/excel_ws.py
xlpie-0.1.0.dist-info/LICENSE
xlpie-0.1.0.dist-info/METADATA
xlpie-0.1.0.dist-info/WHEEL
xlpie-0.1.0.dist-info/RECORD
