Metadata-Version: 2.1
Name: xlpie
Version: 0.1.0
Summary: Python classes for simple MS Excel interactions
License: MIT
Author: PeluxGit
Author-email: 63825662+PeluxGit@users.noreply.github.com
Requires-Python: >=3.10,<4.0
Classifier: License :: OSI Approved :: MIT License
Classifier: Programming Language :: Python :: 3
Classifier: Programming Language :: Python :: 3.10
Classifier: Programming Language :: Python :: 3.11
Requires-Dist: pywin32 (>=305,<306)
Requires-Dist: rich (>=13.3.1,<14.0.0)
